odoo/addons/shopfloor_delivery_shipment/README.rst
odoo/addons/shopfloor_delivery_shipment/__init__.py
odoo/addons/shopfloor_delivery_shipment/__manifest__.py
odoo/addons/shopfloor_delivery_shipment/hooks.py
odoo/addons/shopfloor_delivery_shipment/actions/__init__.py
odoo/addons/shopfloor_delivery_shipment/actions/data.py
odoo/addons/shopfloor_delivery_shipment/actions/message.py
odoo/addons/shopfloor_delivery_shipment/actions/schema.py
odoo/addons/shopfloor_delivery_shipment/actions/search.py
odoo/addons/shopfloor_delivery_shipment/data/shopfloor_scenario_data.xml
odoo/addons/shopfloor_delivery_shipment/demo/shopfloor_app_demo.xml
odoo/addons/shopfloor_delivery_shipment/demo/shopfloor_menu_demo.xml
odoo/addons/shopfloor_delivery_shipment/demo/shopfloor_profile_demo.xml
odoo/addons/shopfloor_delivery_shipment/docs/delivery_shipment_diag_seq.plantuml
odoo/addons/shopfloor_delivery_shipment/docs/delivery_shipment_diag_seq.png
odoo/addons/shopfloor_delivery_shipment/docs/oca_logo.png
odoo/addons/shopfloor_delivery_shipment/i18n/es_AR.po
odoo/addons/shopfloor_delivery_shipment/i18n/it.po
odoo/addons/shopfloor_delivery_shipment/i18n/pt_BR.po
odoo/addons/shopfloor_delivery_shipment/i18n/shopfloor_delivery_shipment.pot
odoo/addons/shopfloor_delivery_shipment/models/__init__.py
odoo/addons/shopfloor_delivery_shipment/models/shopfloor_menu.py
odoo/addons/shopfloor_delivery_shipment/readme/CONTRIBUTORS.rst
odoo/addons/shopfloor_delivery_shipment/readme/CREDITS.rst
odoo/addons/shopfloor_delivery_shipment/readme/DESCRIPTION.rst
odoo/addons/shopfloor_delivery_shipment/services/__init__.py
odoo/addons/shopfloor_delivery_shipment/services/delivery_shipment.py
odoo/addons/shopfloor_delivery_shipment/static/description/icon.png
odoo/addons/shopfloor_delivery_shipment/static/description/index.html
odoo/addons/shopfloor_delivery_shipment/tests/__init__.py
odoo/addons/shopfloor_delivery_shipment/tests/test_delivery_shipment_base.py
odoo14_addon_shopfloor_delivery_shipment-14.0.1.5.0.dist-info/METADATA
odoo14_addon_shopfloor_delivery_shipment-14.0.1.5.0.dist-info/WHEEL
odoo14_addon_shopfloor_delivery_shipment-14.0.1.5.0.dist-info/top_level.txt
odoo14_addon_shopfloor_delivery_shipment-14.0.1.5.0.dist-info/RECORD
